[{"_id":{"$oid":"6906a8831085441df9da83e7"},"requestId":"65b87faf-146e-4b24-bbfd-960f91974fe1","entryId":"2025-11-01-08:00","requesterId":"d79acb13-c8f0-40cd-ba03-6f2d6c518279","reason":"preciso alterar o valor das 8 lancei errado","status":"approved","createdAt":"2025-11-01T21:40:35.934Z","approvedAt":"2025-11-01T22:38:20.863Z","approvedBy":"d79acb13-c8f0-40cd-ba03-6f2d6c518279"},{"_id":{"$oid":"6906d955a1355888e3b0867f"},"requestId":"2349b6c2-4e5f-43a2-a2bc-862e61dffc9e","entryId":"2025-06-15-10:00","requesterId":"8a6b3efc-b071-4a14-9292-b87417fe99a3","requesterName":"maria.santos@iudp.org.br","reason":"Preciso corrigir valor da oferta","status":"approved","createdAt":"2025-11-02T01:08:53.811Z","approvedAt":"2025-11-02T01:24:35.061Z","approvedBy":"d79acb13-c8f0-40cd-ba03-6f2d6c518279"},{"_id":{"$oid":"6906d956a1355888e3b08682"},"requestId":"4fc64182-9298-45f5-a8b2-75d20b23b177","entryId":"2025-06-20-15:00","requesterId":"8a6b3efc-b071-4a14-9292-b87417fe99a3","requesterName":"maria.santos@iudp.org.br","reason":"Necessário corrigir valor informado incorretamente","status":"approved","createdAt":"2025-11-02T01:08:54.027Z","approvedAt":"2025-11-02T01:08:54.348Z","approvedBy":"2bfd0127-6d06-45e8-8836-b264cda2e7cd"},{"_id":{"$oid":"69077af0bbd037fbe0a91e39"},"requestId":"e71211bb-7288-41b3-9938-525d3b32ce95","entryId":"2025-11-01-10:00","requesterId":"d79acb13-c8f0-40cd-ba03-6f2d6c518279","requesterName":"emgec.contato@gmail.com","reason":"AUTORIZA INFORMEI ERRADO","status":"approved","createdAt":"2025-11-02T15:38:24.187Z","approvedAt":"2025-11-03T13:17:42.922Z","approvedBy":"d79acb13-c8f0-40cd-ba03-6f2d6c518279"},{"_id":{"$oid":"6908a96b1203bf20b33a9310"},"requestId":"4692ceb1-b222-4bad-9c98-923ca08a0d26","entryId":"2025-11-01-10:00","requesterId":"d79acb13-c8f0-40cd-ba03-6f2d6c518279","requesterName":"emgec.contato@gmail.com","reason":"nao coloquei por estava atendendo","status":"approved","createdAt":"2025-11-03T13:08:59.101Z","approvedAt":"2025-11-03T13:10:21.479Z","approvedBy":"d79acb13-c8f0-40cd-ba03-6f2d6c518279"},{"_id":{"$oid":"6908ab62cb3f32761040ad3a"},"requestId":"fa3f9a54-462f-4efc-a7b9-72d82dc973a3","entryId":"2025-11-03-08:00","requesterId":"d79acb13-c8f0-40cd-ba03-6f2d6c518279","requesterName":"emgec.contato@gmail.com","reason":"solicito liberacao ","status":"approved","createdAt":"2025-11-03T13:17:22.104Z","approvedAt":"2025-11-03T13:19:43.397Z","approvedBy":"d79acb13-c8f0-40cd-ba03-6f2d6c518279"},{"_id":{"$oid":"6908abe6de6f2307771ec957"},"requestId":"08622820-3b2b-4c4b-82b1-a3a16a295761","entryId":"2025-11-03-08:00","requesterId":"d79acb13-c8f0-40cd-ba03-6f2d6c518279","requesterName":"emgec.contato@gmail.com","reason":"solicito autorizaçao","status":"approved","createdAt":"2025-11-03T13:19:34.242Z","approvedAt":"2025-11-03T13:20:23.517Z","approvedBy":"d79acb13-c8f0-40cd-ba03-6f2d6c518279"},{"_id":{"$oid":"6908ac11de6f2307771ec95a"},"requestId":"3d80d006-d771-4eb7-b347-104749f4e99f","entryId":"2025-11-02-08:00","requesterId":"d79acb13-c8f0-40cd-ba03-6f2d6c518279","requesterName":"emgec.contato@gmail.com","reason":"solicito autorizacao","status":"approved","createdAt":"2025-11-03T13:20:17.458Z","approvedAt":"2025-11-04T14:34:26.677Z","approvedBy":"d79acb13-c8f0-40cd-ba03-6f2d6c518279"},{"_id":{"$oid":"6908ac74de6f2307771ec95d"},"requestId":"fc619f6b-804a-42ee-b63d-1f80a73b3641","entryId":"2025-11-02-10:00","requesterId":"d79acb13-c8f0-40cd-ba03-6f2d6c518279","requesterName":"emgec.contato@gmail.com","reason":"solicito autorizaçao","status":"approved","createdAt":"2025-11-03T13:21:56.663Z","approvedAt":"2025-11-04T14:34:24.998Z","approvedBy":"d79acb13-c8f0-40cd-ba03-6f2d6c518279"},{"_id":{"$oid":"690a0f1169c93dcb2950070e"},"requestId":"8915115a-1e59-49c8-bf8c-ec841f3389c8","entryId":"2025-11-03-10:00","requesterId":"05bab5dc-65b7-415e-aa54-760cfe57330f","requesterName":"novoelielsantos1406@gmail.com","reason":"solicito","status":"approved","createdAt":"2025-11-04T14:34:57.985Z","approvedAt":"2025-11-04T14:35:14.576Z","approvedBy":"d79acb13-c8f0-40cd-ba03-6f2d6c518279"},{"_id":{"$oid":"690a1e9fe4d287aafa223b0c"},"requestId":"11c6ee81-732a-4fa6-871f-5a75fce1fcc1","entryId":null,"day":1,"month":11,"year":2025,"timeSlot":"08:00","requesterId":"58dac8ba-e254-4821-964c-8b1452fdc909","requesterName":"morganbitcons@gmail.com","requesterEmail":"morganbitcons@gmail.com","requesterChurch":"IUDP","requesterRegion":"Paraíba","requesterState":"PB","reason":"Faltou luz, fiquei sem energia para ligar o pc","status":"approved","createdAt":"2025-11-04T15:41:19.706Z","approvedAt":"2025-11-04T15:42:38.819Z","approvedBy":"d79acb13-c8f0-40cd-ba03-6f2d6c518279"},{"_id":{"$oid":"690a20e547e0b4a88e6b521b"},"requestId":"15772fad-78f5-472b-bc84-aba8918de0f6","entryId":null,"day":1,"month":11,"year":2025,"timeSlot":"10:00","requesterId":"58dac8ba-e254-4821-964c-8b1452fdc909","requesterName":"morganbitcons@gmail.com","requesterEmail":"morganbitcons@gmail.com","requesterChurch":"IUDP","requesterRegion":"Paraíba","requesterState":"PB","reason":"Chegou mais oferta depois do horário","status":"approved","createdAt":"2025-11-04T15:51:01.952Z","approvedAt":"2025-11-04T16:01:43.052Z","approvedBy":"d79acb13-c8f0-40cd-ba03-6f2d6c518279"},{"_id":{"$oid":"690a2bb3f581be6afbe7099e"},"requestId":"1f658642-1427-4741-999e-5a1aa1c1de8e","entryId":"2025-11-03-12:00","day":3,"month":11,"year":2025,"timeSlot":"12:00","requesterId":"d79acb13-c8f0-40cd-ba03-6f2d6c518279","requesterName":"emgec.contato@gmail.com","requesterEmail":"emgec.contato@gmail.com","requesterRole":"master","requesterChurch":"SEDE BRASIL","requesterRegion":"SAO PAULO","requesterState":"SAO PAULO","reason":"SOLICITO","status":"approved","createdAt":"2025-11-04T16:37:07.848Z","approvedAt":"2025-11-04T16:38:22.424Z","approvedBy":"d79acb13-c8f0-40cd-ba03-6f2d6c518279"},{"_id":{"$oid":"690c06b5e47e5876a801ca93"},"requestId":"745f9833-fa52-4b5f-b266-254d9035a921","entryId":"2025-11-04-10:00","day":4,"month":11,"year":2025,"timeSlot":"10:00","requesterId":"d79acb13-c8f0-40cd-ba03-6f2d6c518279","requesterName":"emgec.contato@gmail.com","requesterEmail":"emgec.contato@gmail.com","requesterRole":"master","requesterChurch":"","requesterRegion":"SAO PAULO","requesterState":"SAO PAULO","reason":"solicito","status":"approved","createdAt":"2025-11-06T02:23:49.438Z","approvedAt":"2025-11-06T02:24:19.035Z","approvedBy":"d79acb13-c8f0-40cd-ba03-6f2d6c518279"},{"_id":{"$oid":"692054fd8a27963a34924f5a"},"requestId":"de49e79f-0dbd-4bf4-aa1b-a8ab35aadbad","entryId":null,"day":20,"month":11,"year":2025,"timeSlot":"19:30","requesterId":"5d426017-2b99-4e78-8d81-d3bdc8a27a7c","requesterName":"romulosistemas@hotmail.com","requesterEmail":"romulosistemas@hotmail.com","requesterRole":"pastor","requesterChurch":"IUDP - DEUS PROVERÁ","requesterRegion":"","requesterState":"","reason":"Faltou luz na igreja","status":"approved","createdAt":"2025-11-21T12:03:09.333Z","approvedAt":"2025-11-21T12:52:40.141Z","approvedBy":"d79acb13-c8f0-40cd-ba03-6f2d6c518279"},{"_id":{"$oid":"692059a431996bd82fad88f8"},"requestId":"edfeb3a3-fc7f-4166-8cb0-4b5d7818b247","entryId":null,"day":15,"month":11,"year":2025,"timeSlot":"08:00","requesterId":"dbd0944f-3788-40df-8d57-ae42a7e9eb38","requesterName":"pastor.teste@iudp.com","requesterEmail":"pastor.teste@iudp.com","requesterRole":"pastor","requesterChurch":"Igreja Central","requesterRegion":"","requesterState":"SP","reason":"Esqueci de lançar a oferta no dia","status":"approved","createdAt":"2025-11-21T12:23:00.769Z","approvedAt":"2025-11-21T12:23:37.346Z","approvedBy":"1e2e2171-1324-4b3a-8af3-bb63a8177b2a"},{"_id":{"$oid":"692059f1cb18c23fb344e195"},"requestId":"d475270d-8a28-4009-8fe4-ce57463d3671","entryId":null,"day":16,"month":11,"year":2025,"timeSlot":"10:00","requesterId":"dbd0944f-3788-40df-8d57-ae42a7e9eb38","requesterName":"pastor.teste@iudp.com","requesterEmail":"pastor.teste@iudp.com","requesterRole":"pastor","requesterChurch":"Igreja Central","requesterRegion":"","requesterState":"SP","reason":"Teste de solicitação de liberação","status":"approved","createdAt":"2025-11-21T12:24:17.699Z","approvedAt":"2025-11-21T12:24:17.952Z","approvedBy":"1e2e2171-1324-4b3a-8af3-bb63a8177b2a"},{"_id":{"$oid":"69207ebbb05879c436f242df"},"requestId":"910b13a4-658b-4850-bfdc-b972dfab6058","entryId":null,"day":20,"month":11,"year":2025,"timeSlot":"19:30","requesterId":"5d426017-2b99-4e78-8d81-d3bdc8a27a7c","requesterName":"romulosistemas@hotmail.com","requesterEmail":"romulosistemas@hotmail.com","requesterRole":"pastor","requesterChurch":"IUDP - DEUS PROVERÁ","requesterRegion":"","requesterState":"","reason":"Faltou Luz denovo","status":"approved","createdAt":"2025-11-21T15:01:15.301Z","approvedAt":"2025-11-21T15:01:59.490Z","approvedBy":"d79acb13-c8f0-40cd-ba03-6f2d6c518279"},{"_id":{"$oid":"6920a6ea43d12017e5ebccc4"},"requestId":"9da122d8-4827-460e-9f71-81b2d0783bba","entryId":null,"day":21,"month":11,"year":2025,"timeSlot":"10:00","requesterId":"5d426017-2b99-4e78-8d81-d3bdc8a27a7c","requesterName":"romulosistemas@hotmail.com","requesterEmail":"romulosistemas@hotmail.com","requesterRole":"pastor","requesterChurch":"IUDP - DEUS PROVERÁ","requesterRegion":"","requesterState":"","reason":"O fiel atrasou","status":"approved","createdAt":"2025-11-21T17:52:42.563Z","approvedAt":"2025-11-21T18:08:07.063Z","approvedBy":"d79acb13-c8f0-40cd-ba03-6f2d6c518279"},{"_id":{"$oid":"6921c302687ec613af67b25c"},"requestId":"f3cf6a96-c8a1-440c-bf9c-9b2cc6885325","entryId":null,"day":22,"month":11,"year":2025,"timeSlot":"08:00","requesterId":"5d426017-2b99-4e78-8d81-d3bdc8a27a7c","requesterName":"romulosistemas@hotmail.com","requesterEmail":"romulosistemas@hotmail.com","requesterRole":"pastor","requesterChurch":"IUDP - DEUS PROVERÁ","requesterRegion":"","requesterState":"","reason":"solicito liberção perdi o horario estava atendendo","status":"approved","createdAt":"2025-11-22T14:04:50.708Z","approvedAt":"2025-11-22T14:10:15.925Z","approvedBy":"d79acb13-c8f0-40cd-ba03-6f2d6c518279"}]
